MANIFEST.in
README.rst
setup.py
collective/__init__.py
collective.stringinterp.smartlink.egg-info/PKG-INFO
collective.stringinterp.smartlink.egg-info/SOURCES.txt
collective.stringinterp.smartlink.egg-info/dependency_links.txt
collective.stringinterp.smartlink.egg-info/entry_points.txt
collective.stringinterp.smartlink.egg-info/namespace_packages.txt
collective.stringinterp.smartlink.egg-info/not-zip-safe
collective.stringinterp.smartlink.egg-info/requires.txt
collective.stringinterp.smartlink.egg-info/top_level.txt
collective/stringinterp/__init__.py
collective/stringinterp/smartlink/__init__.py
collective/stringinterp/smartlink/adapters.py
collective/stringinterp/smartlink/configure.zcml
collective/stringinterp/smartlink/overrides.zcml
collective/stringinterp/smartlink/locales/collective.stringinterp.smartlink.pot
collective/stringinterp/smartlink/locales/runi18ndude.sh
collective/stringinterp/smartlink/locales/it/LC_MESSAGES/collective.stringinterp.smartlink.mo
collective/stringinterp/smartlink/locales/it/LC_MESSAGES/collective.stringinterp.smartlink.po
docs/HISTORY.txt
docs/INSTALL.txt
docs/LICENSE.GPL
docs/LICENSE.txt