Metadata-Version: 1.1
Name: collective.stringinterp.smartlink
Version: 0.3
Summary: Plone string interpolation override for URLs, with backend-frontend support
Home-page: http://plone.org/products/collective.stringinterp.smartlink
Author: RedTurtle Technology
Author-email: sviluppoplone@redturtle.it
License: GPL
Keywords: plone plonegov e-mail string interpolation
Platform: UNKNOWN
Classifier: Development Status :: 4 - Beta
Classifier: Framework :: Plone
Classifier: Framework :: Plone :: 4.0
Classifier: Framework :: Plone :: 4.1
Classifier: Framework :: Plone :: 4.2
Classifier: Framework :: Plone :: 4.3
Classifier: Programming Language :: Python
